redis_streams/__init__.py
redis_streams/common.py
redis_streams/consumer.py
redis_streams/monitor.py
redis_streams/scaler.py
redis_streams-0.2.0.dist-info/LICENSE
redis_streams-0.2.0.dist-info/METADATA
redis_streams-0.2.0.dist-info/WHEEL
redis_streams-0.2.0.dist-info/top_level.txt
redis_streams-0.2.0.dist-info/RECORD
