Metadata-Version: 2.1
Name: redis-streams
Version: 0.2.0
Summary: Redis Streams client implementation for high availability usage including consumer, monitor and scaler implementation
Home-page: https://github.com/KissPeter/redis-streams/
Author: Peter Kiss
Author-email: peter.kiss@linuxadm.hu
License: GNU General Public License v3.0
Project-URL: Documentation, https://github.com/KissPeter/redis-streams
Project-URL: Changes, https://github.com/KissPeter/redis-streams//releases
Project-URL: Code, https://github.com/KissPeter/redis-streams
Project-URL: Issue tracker, https://github.com/KissPeter/redis-streams//issues
Platform: UNKNOWN
Classifier: Development Status :: 4 - Beta
Classifier: Intended Audience :: Developers
Classifier: Topic :: Communications
Classifier: Topic :: Software Development :: Libraries :: Python Modules
Classifier: Topic :: System :: Distributed Computing
Classifier: Natural Language :: English
Classifier: License :: OSI Approved :: GNU General Public License v3 (GPLv3)
Classifier: Programming Language :: Python :: 3.6
Classifier: Programming Language :: Python :: 3.7
Classifier: Programming Language :: Python :: 3.8
Classifier: Programming Language :: Python :: 3.9
Classifier: Programming Language :: Python :: 3.10
Classifier: Programming Language :: Python :: 3.11
Classifier: Programming Language :: Python :: 3.12
Requires-Python: >=3.6, <4
License-File: LICENSE
